[
    {
        "title": "Macbook Air M4",
        "url": "apple/macbook-air-m4",
        "sku": "APP-L-MA-001",
        "price": "16900",
        "thumb": "apple/macbook-air-m4/display",
        "category": "Electronics > Computers > Laptops",
        "description": "Meet the MacBook Air M4: ultra-thin design, powerful M4 chip, stunning Retina display, and all-day battery—built for speed, style, and portability."
    },
    {
        "title": "Macbook Pro M4 Pro",
        "url": "apple/macbook-pro-m4",
        "sku": "APP-L-MP-M4-002",
        "price": "339000",
        "thumb": "apple/macbook-pro-m4/display",
        "category": "Electronics > Computers > Laptops",
        "description": "Experience top-tier performance with the 2024 MacBook Pro M4 Pro—featuring a 12-core CPU, 16-core GPU, stunning Liquid Retina XDR display, and long-lasting battery life. Ideal for creators, coders, and professionals."
    }
]